topsis_sharv_102303341/__init__.py
topsis_sharv_102303341/topsis.py
topsis_sharv_102303341-1.0.0.dist-info/licenses/LICENSE
topsis_sharv_102303341-1.0.0.dist-info/METADATA
topsis_sharv_102303341-1.0.0.dist-info/WHEEL
topsis_sharv_102303341-1.0.0.dist-info/entry_points.txt
topsis_sharv_102303341-1.0.0.dist-info/top_level.txt
topsis_sharv_102303341-1.0.0.dist-info/RECORD
